tscalcs/__init__.py
tscalcs/exceptions.py
tscalcs/operations.py
tscalcs/utils.py
tscalcs/variable.py
tscalcs-0.1.0.dev4.dist-info/WHEEL
tscalcs-0.1.0.dev4.dist-info/METADATA
tscalcs-0.1.0.dev4.dist-info/RECORD
